djpjax.py
django_pjax-1.7.dist-info/LICENSE
django_pjax-1.7.dist-info/METADATA
django_pjax-1.7.dist-info/WHEEL
django_pjax-1.7.dist-info/top_level.txt
django_pjax-1.7.dist-info/RECORD
