Metadata-Version: 2.1
Name: django-pjax
Version: 1.7
Summary: Django-PJAX: The Django helper for jQuery-PJAX.
Home-page: https://github.com/eventials/django-pjax
Author: Jacob Kaplan-Moss
Author-email: jacob@jacobian.org
Maintainer: Alexandre Vicenzi
Maintainer-email: vicenzi.alexandre@gmail.com
License: BSD
Keywords: django,PJAX,ajax,jQuery
Platform: UNKNOWN
Classifier: Development Status :: 5 - Production/Stable
Classifier: Environment :: Web Environment
Classifier: Framework :: Django
Classifier: Framework :: Django :: 1.4
Classifier: Framework :: Django :: 1.5
Classifier: Framework :: Django :: 1.6
Classifier: Framework :: Django :: 1.7
Classifier: Framework :: Django :: 1.8
Classifier: Intended Audience :: Developers
Classifier: License :: OSI Approved :: BSD License
Classifier: Natural Language :: English
Classifier: Programming Language :: Python
Classifier: Programming Language :: Python :: 2
Classifier: Programming Language :: Python :: 2.6
Classifier: Programming Language :: Python :: 2.7
Classifier: Programming Language :: Python :: 3
Classifier: Programming Language :: Python :: 3.2
Classifier: Programming Language :: Python :: 3.3
Classifier: Programming Language :: Python :: 3.4
Classifier: Programming Language :: Python :: Implementation :: CPython
Classifier: Programming Language :: Python :: Implementation :: PyPy
Requires-Dist: django (>=1.3)
